odoo/addons/repair_discount/README.rst
odoo/addons/repair_discount/__init__.py
odoo/addons/repair_discount/__manifest__.py
odoo/addons/repair_discount/i18n/de.po
odoo/addons/repair_discount/i18n/es.po
odoo/addons/repair_discount/i18n/fr.po
odoo/addons/repair_discount/i18n/hr.po
odoo/addons/repair_discount/i18n/hr_HR.po
odoo/addons/repair_discount/i18n/it.po
odoo/addons/repair_discount/i18n/lt.po
odoo/addons/repair_discount/i18n/mrp_repair_discount.pot
odoo/addons/repair_discount/i18n/nl_NL.po
odoo/addons/repair_discount/i18n/pt_BR.po
odoo/addons/repair_discount/i18n/repair_discount.pot
odoo/addons/repair_discount/models/__init__.py
odoo/addons/repair_discount/models/mrp_repair.py
odoo/addons/repair_discount/readme/CONTRIBUTORS.rst
odoo/addons/repair_discount/readme/DESCRIPTION.rst
odoo/addons/repair_discount/report/repair_templates_repair_order.xml
odoo/addons/repair_discount/static/description/icon.png
odoo/addons/repair_discount/static/description/index.html
odoo/addons/repair_discount/tests/__init__.py
odoo/addons/repair_discount/tests/test_mrp_repair_discount.py
odoo/addons/repair_discount/views/mrp_repair_view.xml
odoo14_addon_repair_discount-14.0.1.0.1.dev11.dist-info/METADATA
odoo14_addon_repair_discount-14.0.1.0.1.dev11.dist-info/WHEEL
odoo14_addon_repair_discount-14.0.1.0.1.dev11.dist-info/top_level.txt
odoo14_addon_repair_discount-14.0.1.0.1.dev11.dist-info/RECORD
